coloray/__init__.py
coloray-0.1.1.dist-info/licenses/LICENSE
coloray-0.1.1.dist-info/METADATA
coloray-0.1.1.dist-info/WHEEL
coloray-0.1.1.dist-info/top_level.txt
coloray-0.1.1.dist-info/RECORD
