Metadata-Version: 2.4
Name: coloray
Version: 0.1.1
Summary: Minimal Python library for colored terminal output
Author: leafcss
Author-email: leafcss <leo@leafmc.cc>
License:                     GNU AFFERO GENERAL PUBLIC LICENSE
Project-URL: Homepage, https://github.com/leafcss/coloray
Keywords: color,terminal,style,rgb,hex,ansi
Classifier: Development Status :: 4 - Beta
Classifier: Programming Language :: Python :: 3
Classifier: License :: OSI Approved :: GNU Affero General Public License v3
Classifier: Topic :: Software Development :: Libraries
Classifier: Environment :: Console
Requires-Python: >=3.6
License-File: LICENSE
Dynamic: license-file
